gcscore/__init__.py
gcscore/_command_renderer.py
gcscore/_commons.py
gcscore/_error_history.py
gcscore/_j2ext.py
gcscore/mod/__init__.py
gcscore/mod/_base.py
gcscore/mod/_context.py
gcscore/mod/_helpers.py
gcscore/mod/_visitor.py
gcscore/mod/validation.py
gcscore-0.0.22.dist-info/LICENSE
gcscore-0.0.22.dist-info/METADATA
gcscore-0.0.22.dist-info/WHEEL
gcscore-0.0.22.dist-info/top_level.txt
gcscore-0.0.22.dist-info/RECORD
