Metadata-Version: 2.1
Name: gcscore
Version: 0.0.22
Summary: Generic Command System, a tool to help the creation of custom procedures.
Author-email: Leikt <leikt.solreihin@gmail.com>
Classifier: Programming Language :: Python :: 3
Classifier: License :: OSI Approved :: MIT License
Classifier: Operating System :: OS Independent
Requires-Python: >=3.9
License-File: LICENSE
Requires-Dist: Jinja2 (>=3.1.2)
Requires-Dist: jsonpath-ng (>=1.5.3)
Requires-Dist: toml (>=0.10.2)
